[{"time": 1634958005.438737, "data": [{"station_id": "328", "bikes_available": 0, "docks_available": 17, "ebikes_avaiable": 0}, {"station_id": "345", "bikes_available": 4, "docks_available": 15, "ebikes_avaiable": 1}, {"station_id": "420", "bikes_available": 5, "docks_available": 13, "ebikes_avaiable": 0}, {"station_id": "423", "bikes_available": 0, "docks_available": 29, "ebikes_avaiable": 0}, {"station_id": "424", "bikes_available": 5, "docks_available": 20, "ebikes_avaiable": 1}, {"station_id": "425", "bikes_available": 10, "docks_available": 4, "ebikes_avaiable": 0}, {"station_id": "426", "bikes_available": 5, "docks_available": 14, "ebikes_avaiable": 0}]}, {"time": 1634958066.0609367, "data": [{"station_id": "328", "bikes_available": 0, "docks_available": 17, "ebikes_avaiable": 0}, {"station_id": "345", "bikes_available": 4, "docks_available": 15, "ebikes_avaiable": 1}, {"station_id": "420", "bikes_available": 5, "docks_available": 13, "ebikes_avaiable": 0}, {"station_id": "423", "bikes_available": 0, "docks_available": 29, "ebikes_avaiable": 0}, {"station_id": "424", "bikes_available": 5, "docks_available": 20, "ebikes_avaiable": 1}, {"station_id": "425", "bikes_available": 10, "docks_available": 4, "ebikes_avaiable": 0}, {"station_id": "426", "bikes_available": 8, "docks_available": 11, "ebikes_avaiable": 1}]}, {"time": 1634958126.7857487, "data": [{"station_id": "328", "bikes_available": 0, "docks_available": 17, "ebikes_avaiable": 0}, {"station_id": "345", "bikes_available": 4, "docks_available": 15, "ebikes_avaiable": 1}, {"station_id": "420", "bikes_available": 5, "docks_available": 13, "ebikes_avaiable": 0}, {"station_id": "423", "bikes_available": 0, "docks_available": 29, "ebikes_avaiable": 0}, {"station_id": "424", "bikes_available": 5, "docks_available": 20, "ebikes_avaiable": 1}, {"station_id": "425", "bikes_available": 10, "docks_available": 4, "ebikes_avaiable": 0}, {"station_id": "426", "bikes_available": 8, "docks_available": 11, "ebikes_avaiable": 1}]}, {"time": 1634958187.4211988, "data": [{"station_id": "328", "bikes_available": 0, "docks_available": 17, "ebikes_avaiable": 0}, {"station_id": "345", "bikes_available": 4, "docks_available": 15, "ebikes_avaiable": 1}, {"station_id": "420", "bikes_available": 5, "docks_available": 13, "ebikes_avaiable": 0}, {"station_id": "423", "bikes_available": 0, "docks_available": 29, "ebikes_avaiable": 0}, {"station_id": "424", "bikes_available": 5, "docks_available": 20, "ebikes_avaiable": 1}, {"station_id": "425", "bikes_available": 10, "docks_available": 4, "ebikes_avaiable": 0}, {"station_id": "426", "bikes_available": 8, "docks_available": 11, "ebikes_avaiable": 1}]}, {"time": 1634958247.9956498, "data": [{"station_id": "328", "bikes_available": 0, "docks_available": 17, "ebikes_avaiable": 0}, {"station_id": "345", "bikes_available": 5, "docks_available": 14, "ebikes_avaiable": 2}, {"station_id": "420", "bikes_available": 5, "docks_available": 13, "ebikes_avaiable": 0}, {"station_id": "423", "bikes_available": 0, "docks_available": 29, "ebikes_avaiable": 0}, {"station_id": "424", "bikes_available": 5, "docks_available": 20, "ebikes_avaiable": 1}, {"station_id": "425", "bikes_available": 10, "docks_available": 4, "ebikes_avaiable": 0}, {"station_id": "426", "bikes_available": 8, "docks_available": 11, "ebikes_avaiable": 1}]}, {"time": 1634958308.660349, "data": [{"station_id": "328", "bikes_available": 0, "docks_available": 17, "ebikes_avaiable": 0}, {"station_id": "345", "bikes_available": 5, "docks_available": 14, "ebikes_avaiable": 2}, {"station_id": "420", "bikes_available": 4, "docks_available": 14, "ebikes_avaiable": 0}, {"station_id": "423", "bikes_available": 0, "docks_available": 29, "ebikes_avaiable": 0}, {"station_id": "424", "bikes_available": 5, "docks_available": 20, "ebikes_avaiable": 1}, {"station_id": "425", "bikes_available": 10, "docks_available": 4, "ebikes_avaiable": 0}, {"station_id": "426", "bikes_available": 8, "docks_available": 11, "ebikes_avaiable": 1}]}, {"time": 1634958369.300577, "data": [{"station_id": "328", "bikes_available": 0, "docks_available": 17, "ebikes_avaiable": 0}, {"station_id": "345", "bikes_available": 5, "docks_available": 14, "ebikes_avaiable": 2}, {"station_id": "420", "bikes_available": 4, "docks_available": 14, "ebikes_avaiable": 0}, {"station_id": "423", "bikes_available": 0, "docks_available": 29, "ebikes_avaiable": 0}, {"station_id": "424", "bikes_available": 4, "docks_available": 21, "ebikes_avaiable": 0}, {"station_id": "425", "bikes_available": 10, "docks_available": 4, "ebikes_avaiable": 0}, {"station_id": "426", "bikes_available": 8, "docks_available": 11, "ebikes_avaiable": 1}]}, {"time": 1634958429.9602256, "data": [{"station_id": "328", "bikes_available": 0, "docks_available": 17, "ebikes_avaiable": 0}, {"station_id": "345", "bikes_available": 5, "docks_available": 14, "ebikes_avaiable": 2}, {"station_id": "420", "bikes_available": 4, "docks_available": 14, "ebikes_avaiable": 0}, {"station_id": "423", "bikes_available": 2, "docks_available": 27, "ebikes_avaiable": 1}, {"station_id": "424", "bikes_available": 4, "docks_available": 21, "ebikes_avaiable": 0}, {"station_id": "425", "bikes_available": 10, "docks_available": 4, "ebikes_avaiable": 0}, {"station_id": "426", "bikes_available": 8, "docks_available": 11, "ebikes_avaiable": 1}]}, {"time": 1634958490.5050328, "data": [{"station_id": "328", "bikes_available": 0, "docks_available": 17, "ebikes_avaiable": 0}, {"station_id": "345", "bikes_available": 5, "docks_available": 14, "ebikes_avaiable": 2}, {"station_id": "420", "bikes_available": 4, "docks_available": 14, "ebikes_avaiable": 0}, {"station_id": "423", "bikes_available": 2, "docks_available": 27, "ebikes_avaiable": 1}, {"station_id": "424", "bikes_available": 4, "docks_available": 21, "ebikes_avaiable": 0}, {"station_id": "425", "bikes_available": 10, "docks_available": 4, "ebikes_avaiable": 0}, {"station_id": "426", "bikes_available": 9, "docks_available": 10, "ebikes_avaiable": 1}]}, {"time": 1634958551.177282, "data": [{"station_id": "328", "bikes_available": 0, "docks_available": 17, "ebikes_avaiable": 0}, {"station_id": "345", "bikes_available": 5, "docks_available": 14, "ebikes_avaiable": 2}, {"station_id": "420", "bikes_available": 4, "docks_available": 14, "ebikes_avaiable": 0}, {"station_id": "423", "bikes_available": 2, "docks_available": 27, "ebikes_avaiable": 1}, {"station_id": "424", "bikes_available": 4, "docks_available": 21, "ebikes_avaiable": 0}, {"station_id": "425", "bikes_available": 10, "docks_available": 4, "ebikes_avaiable": 0}, {"station_id": "426", "bikes_available": 9, "docks_available": 10, "ebikes_avaiable": 1}]}, {"time": 1634958611.8251758, "data": [{"station_id": "328", "bikes_available": 0, "docks_available": 17, "ebikes_avaiable": 0}, {"station_id": "345", "bikes_available": 5, "docks_available": 14, "ebikes_avaiable": 2}, {"station_id": "420", "bikes_available": 4, "docks_available": 14, "ebikes_avaiable": 0}, {"station_id": "423", "bikes_available": 2, "docks_available": 27, "ebikes_avaiable": 1}, {"station_id": "424", "bikes_available": 4, "docks_available": 21, "ebikes_avaiable": 0}, {"station_id": "425", "bikes_available": 10, "docks_available": 4, "ebikes_avaiable": 0}, {"station_id": "426", "bikes_available": 9, "docks_available": 10, "ebikes_avaiable": 1}]}, {"time": 1634958672.6220577, "data": [{"station_id": "328", "bikes_available": 0, "docks_available": 17, "ebikes_avaiable": 0}, {"station_id": "345", "bikes_available": 5, "docks_available": 14, "ebikes_avaiable": 2}, {"station_id": "420", "bikes_available": 4, "docks_available": 14, "ebikes_avaiable": 0}, {"station_id": "423", "bikes_available": 2, "docks_available": 27, "ebikes_avaiable": 1}, {"station_id": "424", "bikes_available": 4, "docks_available": 21, "ebikes_avaiable": 0}, {"station_id": "425", "bikes_available": 10, "docks_available": 4, "ebikes_avaiable": 0}, {"station_id": "426", "bikes_available": 9, "docks_available": 10, "ebikes_avaiable": 1}]}, {"time": 1634958733.188501, "data": [{"station_id": "328", "bikes_available": 0, "docks_available": 17, "ebikes_avaiable": 0}, {"station_id": "345", "bikes_available": 4, "docks_available": 15, "ebikes_avaiable": 2}, {"station_id": "420", "bikes_available": 4, "docks_available": 14, "ebikes_avaiable": 0}, {"station_id": "423", "bikes_available": 2, "docks_available": 27, "ebikes_avaiable": 1}, {"station_id": "424", "bikes_available": 4, "docks_available": 21, "ebikes_avaiable": 0}, {"station_id": "425", "bikes_available": 10, "docks_available": 4, "ebikes_avaiable": 0}, {"station_id": "426", "bikes_available": 9, "docks_available": 10, "ebikes_avaiable": 1}]}, {"time": 1634958793.8115864, "data": [{"station_id": "328", "bikes_available": 0, "docks_available": 17, "ebikes_avaiable": 0}, {"station_id": "345", "bikes_available": 4, "docks_available": 15, "ebikes_avaiable": 2}, {"station_id": "420", "bikes_available": 4, "docks_available": 14, "ebikes_avaiable": 0}, {"station_id": "423", "bikes_available": 2, "docks_available": 27, "ebikes_avaiable": 1}, {"station_id": "424", "bikes_available": 4, "docks_available": 21, "ebikes_avaiable": 0}, {"station_id": "425", "bikes_available": 10, "docks_available": 4, "ebikes_avaiable": 0}, {"station_id": "426", "bikes_available": 9, "docks_available": 10, "ebikes_avaiable": 1}]}, {"time": 1634958854.4598744, "data": [{"station_id": "328", "bikes_available": 0, "docks_available": 17, "ebikes_avaiable": 0}, {"station_id": "345", "bikes_available": 4, "docks_available": 15, "ebikes_avaiable": 2}, {"station_id": "420", "bikes_available": 4, "docks_available": 14, "ebikes_avaiable": 0}, {"station_id": "423", "bikes_available": 1, "docks_available": 28, "ebikes_avaiable": 1}, {"station_id": "424", "bikes_available": 4, "docks_available": 21, "ebikes_avaiable": 0}, {"station_id": "425", "bikes_available": 10, "docks_available": 4, "ebikes_avaiable": 0}, {"station_id": "426", "bikes_available": 9, "docks_available": 10, "ebikes_avaiable": 1}]}, {"time": 1634958915.124453, "data": [{"station_id": "328", "bikes_available": 0, "docks_available": 17, "ebikes_avaiable": 0}, {"station_id": "345", "bikes_available": 4, "docks_available": 15, "ebikes_avaiable": 2}, {"station_id": "420", "bikes_available": 4, "docks_available": 14, "ebikes_avaiable": 0}, {"station_id": "423", "bikes_available": 1, "docks_available": 28, "ebikes_avaiable": 1}, {"station_id": "424", "bikes_available": 4, "docks_available": 21, "ebikes_avaiable": 0}, {"station_id": "425", "bikes_available": 10, "docks_available": 4, "ebikes_avaiable": 0}, {"station_id": "426", "bikes_available": 9, "docks_available": 10, "ebikes_avaiable": 1}]}, {"time": 1634958975.8149664, "data": [{"station_id": "328", "bikes_available": 0, "docks_available": 17, "ebikes_avaiable": 0}, {"station_id": "345", "bikes_available": 4, "docks_available": 15, "ebikes_avaiable": 2}, {"station_id": "420", "bikes_available": 4, "docks_available": 14, "ebikes_avaiable": 0}, {"station_id": "423", "bikes_available": 1, "docks_available": 28, "ebikes_avaiable": 1}, {"station_id": "424", "bikes_available": 4, "docks_available": 21, "ebikes_avaiable": 0}, {"station_id": "425", "bikes_available": 10, "docks_available": 4, "ebikes_avaiable": 0}, {"station_id": "426", "bikes_available": 9, "docks_available": 10, "ebikes_avaiable": 1}]}, {"time": 1634959037.0871484, "data": [{"station_id": "328", "bikes_available": 0, "docks_available": 17, "ebikes_avaiable": 0}, {"station_id": "345", "bikes_available": 4, "docks_available": 15, "ebikes_avaiable": 2}, {"station_id": "420", "bikes_available": 4, "docks_available": 14, "ebikes_avaiable": 0}, {"station_id": "423", "bikes_available": 0, "docks_available": 29, "ebikes_avaiable": 0}, {"station_id": "424", "bikes_available": 4, "docks_available": 21, "ebikes_avaiable": 0}, {"station_id": "425", "bikes_available": 10, "docks_available": 4, "ebikes_avaiable": 0}, {"station_id": "426", "bikes_available": 9, "docks_available": 10, "ebikes_avaiable": 1}]}, {"time": 1634959097.670455, "data": [{"station_id": "328", "bikes_available": 0, "docks_available": 17, "ebikes_avaiable": 0}, {"station_id": "345", "bikes_available": 4, "docks_available": 15, "ebikes_avaiable": 2}, {"station_id": "420", "bikes_available": 4, "docks_available": 14, "ebikes_avaiable": 0}, {"station_id": "423", "bikes_available": 0, "docks_available": 29, "ebikes_avaiable": 0}, {"station_id": "424", "bikes_available": 4, "docks_available": 21, "ebikes_avaiable": 0}, {"station_id": "425", "bikes_available": 10, "docks_available": 4, "ebikes_avaiable": 0}, {"station_id": "426", "bikes_available": 10, "docks_available": 9, "ebikes_avaiable": 1}]}, {"time": 1634959158.286095, "data": [{"station_id": "328", "bikes_available": 0, "docks_available": 17, "ebikes_avaiable": 0}, {"station_id": "345", "bikes_available": 4, "docks_available": 15, "ebikes_avaiable": 2}, {"station_id": "420", "bikes_available": 4, "docks_available": 14, "ebikes_avaiable": 0}, {"station_id": "423", "bikes_available": 0, "docks_available": 29, "ebikes_avaiable": 0}, {"station_id": "424", "bikes_available": 4, "docks_available": 21, "ebikes_avaiable": 0}, {"station_id": "425", "bikes_available": 10, "docks_available": 4, "ebikes_avaiable": 0}, {"station_id": "426", "bikes_available": 10, "docks_available": 9, "ebikes_avaiable": 1}]}, {"time": 1634959218.9134886, "data": [{"station_id": "328", "bikes_available": 0, "docks_available": 17, "ebikes_avaiable": 0}, {"station_id": "345", "bikes_available": 4, "docks_available": 15, "ebikes_avaiable": 2}, {"station_id": "420", "bikes_available": 4, "docks_available": 14, "ebikes_avaiable": 0}, {"station_id": "423", "bikes_available": 0, "docks_available": 29, "ebikes_avaiable": 0}, {"station_id": "424", "bikes_available": 4, "docks_available": 21, "ebikes_avaiable": 0}, {"station_id": "425", "bikes_available": 10, "docks_available": 4, "ebikes_avaiable": 0}, {"station_id": "426", "bikes_available": 11, "docks_available": 8, "ebikes_avaiable": 2}]}, {"time": 1634959279.5070415, "data": [{"station_id": "328", "bikes_available": 0, "docks_available": 17, "ebikes_avaiable": 0}, {"station_id": "345", "bikes_available": 4, "docks_available": 15, "ebikes_avaiable": 2}, {"station_id": "420", "bikes_available": 3, "docks_available": 15, "ebikes_avaiable": 0}, {"station_id": "423", "bikes_available": 0, "docks_available": 29, "ebikes_avaiable": 0}, {"station_id": "424", "bikes_available": 4, "docks_available": 21, "ebikes_avaiable": 0}, {"station_id": "425", "bikes_available": 10, "docks_available": 4, "ebikes_avaiable": 0}, {"station_id": "426", "bikes_available": 11, "docks_available": 8, "ebikes_avaiable": 2}]}, {"time": 1634959340.1693614, "data": [{"station_id": "328", "bikes_available": 0, "docks_available": 17, "ebikes_avaiable": 0}, {"station_id": "345", "bikes_available": 4, "docks_available": 15, "ebikes_avaiable": 2}, {"station_id": "420", "bikes_available": 3, "docks_available": 15, "ebikes_avaiable": 0}, {"station_id": "423", "bikes_available": 0, "docks_available": 29, "ebikes_avaiable": 0}, {"station_id": "424", "bikes_available": 4, "docks_available": 21, "ebikes_avaiable": 0}, {"station_id": "425", "bikes_available": 10, "docks_available": 4, "ebikes_avaiable": 0}, {"station_id": "426", "bikes_available": 11, "docks_available": 8, "ebikes_avaiable": 2}]}, {"time": 1634959400.8063052, "data": [{"station_id": "328", "bikes_available": 0, "docks_available": 17, "ebikes_avaiable": 0}, {"station_id": "345", "bikes_available": 4, "docks_available": 15, "ebikes_avaiable": 2}, {"station_id": "420", "bikes_available": 3, "docks_available": 15, "ebikes_avaiable": 0}, {"station_id": "423", "bikes_available": 0, "docks_available": 29, "ebikes_avaiable": 0}, {"station_id": "424", "bikes_available": 4, "docks_available": 21, "ebikes_avaiable": 0}, {"station_id": "425", "bikes_available": 10, "docks_available": 4, "ebikes_avaiable": 0}, {"station_id": "426", "bikes_available": 11, "docks_available": 8, "ebikes_avaiable": 2}]}, {"time": 1634959461.5016773, "data": [{"station_id": "328", "bikes_available": 0, "docks_available": 17, "ebikes_avaiable": 0}, {"station_id": "345", "bikes_available": 4, "docks_available": 15, "ebikes_avaiable": 2}, {"station_id": "420", "bikes_available": 3, "docks_available": 15, "ebikes_avaiable": 0}, {"station_id": "423", "bikes_available": 0, "docks_available": 29, "ebikes_avaiable": 0}, {"station_id": "424", "bikes_available": 4, "docks_available": 21, "ebikes_avaiable": 0}, {"station_id": "425", "bikes_available": 10, "docks_available": 4, "ebikes_avaiable": 0}, {"station_id": "426", "bikes_available": 11, "docks_available": 8, "ebikes_avaiable": 2}]}, {"time": 1634959522.2670815, "data": [{"station_id": "328", "bikes_available": 0, "docks_available": 17, "ebikes_avaiable": 0}, {"station_id": "345", "bikes_available": 4, "docks_available": 15, "ebikes_avaiable": 2}, {"station_id": "420", "bikes_available": 2, "docks_available": 16, "ebikes_avaiable": 0}, {"station_id": "423", "bikes_available": 0, "docks_available": 29, "ebikes_avaiable": 0}, {"station_id": "424", "bikes_available": 4, "docks_available": 21, "ebikes_avaiable": 0}, {"station_id": "425", "bikes_available": 10, "docks_available": 4, "ebikes_avaiable": 0}, {"station_id": "426", "bikes_available": 12, "docks_available": 7, "ebikes_avaiable": 2}]}, {"time": 1634959583.44327, "data": [{"station_id": "328", "bikes_available": 0, "docks_available": 17, "ebikes_avaiable": 0}, {"station_id": "345", "bikes_available": 4, "docks_available": 15, "ebikes_avaiable": 2}, {"station_id": "420", "bikes_available": 2, "docks_available": 16, "ebikes_avaiable": 0}, {"station_id": "423", "bikes_available": 0, "docks_available": 29, "ebikes_avaiable": 0}, {"station_id": "424", "bikes_available": 4, "docks_available": 21, "ebikes_avaiable": 0}, {"station_id": "425", "bikes_available": 10, "docks_available": 4, "ebikes_avaiable": 0}, {"station_id": "426", "bikes_available": 12, "docks_available": 7, "ebikes_avaiable": 2}]}, {"time": 1634959644.6114008, "data": [{"station_id": "328", "bikes_available": 0, "docks_available": 17, "ebikes_avaiable": 0}, {"station_id": "345", "bikes_available": 4, "docks_available": 15, "ebikes_avaiable": 2}, {"station_id": "420", "bikes_available": 2, "docks_available": 16, "ebikes_avaiable": 0}, {"station_id": "423", "bikes_available": 0, "docks_available": 29, "ebikes_avaiable": 0}, {"station_id": "424", "bikes_available": 4, "docks_available": 21, "ebikes_avaiable": 0}, {"station_id": "425", "bikes_available": 10, "docks_available": 4, "ebikes_avaiable": 0}, {"station_id": "426", "bikes_available": 12, "docks_available": 7, "ebikes_avaiable": 2}]}, {"time": 1634959705.1801322, "data": [{"station_id": "328", "bikes_available": 0, "docks_available": 17, "ebikes_avaiable": 0}, {"station_id": "345", "bikes_available": 4, "docks_available": 15, "ebikes_avaiable": 2}, {"station_id": "420", "bikes_available": 2, "docks_available": 16, "ebikes_avaiable": 0}, {"station_id": "423", "bikes_available": 0, "docks_available": 29, "ebikes_avaiable": 0}, {"station_id": "424", "bikes_available": 4, "docks_available": 21, "ebikes_avaiable": 0}, {"station_id": "425", "bikes_available": 10, "docks_available": 4, "ebikes_avaiable": 0}, {"station_id": "426", "bikes_available": 12, "docks_available": 7, "ebikes_avaiable": 2}]}, {"time": 1634959765.7905188, "data": [{"station_id": "328", "bikes_available": 0, "docks_available": 17, "ebikes_avaiable": 0}, {"station_id": "345", "bikes_available": 4, "docks_available": 15, "ebikes_avaiable": 2}, {"station_id": "420", "bikes_available": 2, "docks_available": 16, "ebikes_avaiable": 0}, {"station_id": "423", "bikes_available": 0, "docks_available": 29, "ebikes_avaiable": 0}, {"station_id": "424", "bikes_available": 4, "docks_available": 21, "ebikes_avaiable": 0}, {"station_id": "425", "bikes_available": 10, "docks_available": 4, "ebikes_avaiable": 0}, {"station_id": "426", "bikes_available": 13, "docks_available": 6, "ebikes_avaiable": 2}]}, {"time": 1634959826.4522116, "data": [{"station_id": "328", "bikes_available": 0, "docks_available": 17, "ebikes_avaiable": 0}, {"station_id": "345", "bikes_available": 4, "docks_available": 15, "ebikes_avaiable": 2}, {"station_id": "420", "bikes_available": 2, "docks_available": 16, "ebikes_avaiable": 0}, {"station_id": "423", "bikes_available": 0, "docks_available": 29, "ebikes_avaiable": 0}, {"station_id": "424", "bikes_available": 4, "docks_available": 21, "ebikes_avaiable": 0}, {"station_id": "425", "bikes_available": 10, "docks_available": 4, "ebikes_avaiable": 0}, {"station_id": "426", "bikes_available": 13, "docks_available": 6, "ebikes_avaiable": 2}]}, {"time": 1634959887.1674724, "data": [{"station_id": "328", "bikes_available": 0, "docks_available": 17, "ebikes_avaiable": 0}, {"station_id": "345", "bikes_available": 4, "docks_available": 15, "ebikes_avaiable": 2}, {"station_id": "420", "bikes_available": 2, "docks_available": 16, "ebikes_avaiable": 0}, {"station_id": "423", "bikes_available": 0, "docks_available": 29, "ebikes_avaiable": 0}, {"station_id": "424", "bikes_available": 4, "docks_available": 21, "ebikes_avaiable": 0}, {"station_id": "425", "bikes_available": 10, "docks_available": 4, "ebikes_avaiable": 0}, {"station_id": "426", "bikes_available": 13, "docks_available": 6, "ebikes_avaiable": 2}]}, {"time": 1634959947.726426, "data": [{"station_id": "328", "bikes_available": 0, "docks_available": 17, "ebikes_avaiable": 0}, {"station_id": "345", "bikes_available": 4, "docks_available": 15, "ebikes_avaiable": 2}, {"station_id": "420", "bikes_available": 2, "docks_available": 16, "ebikes_avaiable": 0}, {"station_id": "423", "bikes_available": 0, "docks_available": 29, "ebikes_avaiable": 0}, {"station_id": "424", "bikes_available": 4, "docks_available": 21, "ebikes_avaiable": 0}, {"station_id": "425", "bikes_available": 10, "docks_available": 4, "ebikes_avaiable": 0}, {"station_id": "426", "bikes_available": 12, "docks_available": 7, "ebikes_avaiable": 2}]}, {"time": 1634960008.3640137, "data": [{"station_id": "328", "bikes_available": 0, "docks_available": 17, "ebikes_avaiable": 0}, {"station_id": "345", "bikes_available": 4, "docks_available": 15, "ebikes_avaiable": 2}, {"station_id": "420", "bikes_available": 2, "docks_available": 16, "ebikes_avaiable": 0}, {"station_id": "423", "bikes_available": 0, "docks_available": 29, "ebikes_avaiable": 0}, {"station_id": "424", "bikes_available": 4, "docks_available": 21, "ebikes_avaiable": 0}, {"station_id": "425", "bikes_available": 10, "docks_available": 4, "ebikes_avaiable": 0}, {"station_id": "426", "bikes_available": 12, "docks_available": 7, "ebikes_avaiable": 2}]}, {"time": 1634960068.9634233, "data": [{"station_id": "328", "bikes_available": 0, "docks_available": 17, "ebikes_avaiable": 0}, {"station_id": "345", "bikes_available": 4, "docks_available": 15, "ebikes_avaiable": 2}, {"station_id": "420", "bikes_available": 2, "docks_available": 16, "ebikes_avaiable": 0}, {"station_id": "423", "bikes_available": 0, "docks_available": 29, "ebikes_avaiable": 0}, {"station_id": "424", "bikes_available": 4, "docks_available": 21, "ebikes_avaiable": 0}, {"station_id": "425", "bikes_available": 10, "docks_available": 4, "ebikes_avaiable": 0}, {"station_id": "426", "bikes_available": 12, "docks_available": 7, "ebikes_avaiable": 2}]}, {"time": 1634960129.7637389, "data": [{"station_id": "328", "bikes_available": 0, "docks_available": 17, "ebikes_avaiable": 0}, {"station_id": "345", "bikes_available": 4, "docks_available": 15, "ebikes_avaiable": 2}, {"station_id": "420", "bikes_available": 2, "docks_available": 16, "ebikes_avaiable": 0}, {"station_id": "423", "bikes_available": 0, "docks_available": 29, "ebikes_avaiable": 0}, {"station_id": "424", "bikes_available": 4, "docks_available": 21, "ebikes_avaiable": 0}, {"station_id": "425", "bikes_available": 10, "docks_available": 4, "ebikes_avaiable": 0}, {"station_id": "426", "bikes_available": 12, "docks_available": 7, "ebikes_avaiable": 2}]}, {"time": 1634960190.4089308, "data": [{"station_id": "328", "bikes_available": 0, "docks_available": 17, "ebikes_avaiable": 0}, {"station_id": "345", "bikes_available": 4, "docks_available": 15, "ebikes_avaiable": 2}, {"station_id": "420", "bikes_available": 3, "docks_available": 15, "ebikes_avaiable": 0}, {"station_id": "423", "bikes_available": 0, "docks_available": 29, "ebikes_avaiable": 0}, {"station_id": "424", "bikes_available": 4, "docks_available": 21, "ebikes_avaiable": 0}, {"station_id": "425", "bikes_available": 10, "docks_available": 4, "ebikes_avaiable": 0}, {"station_id": "426", "bikes_available": 12, "docks_available": 7, "ebikes_avaiable": 2}]}, {"time": 1634960251.0493011, "data": [{"station_id": "328", "bikes_available": 0, "docks_available": 17, "ebikes_avaiable": 0}, {"station_id": "345", "bikes_available": 4, "docks_available": 15, "ebikes_avaiable": 2}, {"station_id": "420", "bikes_available": 3, "docks_available": 15, "ebikes_avaiable": 0}, {"station_id": "423", "bikes_available": 0, "docks_available": 29, "ebikes_avaiable": 0}, {"station_id": "424", "bikes_available": 4, "docks_available": 21, "ebikes_avaiable": 0}, {"station_id": "425", "bikes_available": 10, "docks_available": 4, "ebikes_avaiable": 0}, {"station_id": "426", "bikes_available": 12, "docks_available": 7, "ebikes_avaiable": 2}]}, {"time": 1634960311.804037, "data": [{"station_id": "328", "bikes_available": 0, "docks_available": 17, "ebikes_avaiable": 0}, {"station_id": "345", "bikes_available": 4, "docks_available": 15, "ebikes_avaiable": 2}, {"station_id": "420", "bikes_available": 3, "docks_available": 15, "ebikes_avaiable": 0}, {"station_id": "423", "bikes_available": 0, "docks_available": 29, "ebikes_avaiable": 0}, {"station_id": "424", "bikes_available": 4, "docks_available": 21, "ebikes_avaiable": 0}, {"station_id": "425", "bikes_available": 10, "docks_available": 4, "ebikes_avaiable": 0}, {"station_id": "426", "bikes_available": 12, "docks_available": 7, "ebikes_avaiable": 2}]}, {"time": 1634960372.7734616, "data": [{"station_id": "328", "bikes_available": 0, "docks_available": 17, "ebikes_avaiable": 0}, {"station_id": "345", "bikes_available": 4, "docks_available": 15, "ebikes_avaiable": 2}, {"station_id": "420", "bikes_available": 3, "docks_available": 15, "ebikes_avaiable": 0}, {"station_id": "423", "bikes_available": 0, "docks_available": 29, "ebikes_avaiable": 0}, {"station_id": "424", "bikes_available": 4, "docks_available": 21, "ebikes_avaiable": 0}, {"station_id": "425", "bikes_available": 10, "docks_available": 4, "ebikes_avaiable": 0}, {"station_id": "426", "bikes_available": 12, "docks_available": 7, "ebikes_avaiable": 2}]}, {"time": 1634960433.3151736, "data": [{"station_id": "328", "bikes_available": 0, "docks_available": 17, "ebikes_avaiable": 0}, {"station_id": "345", "bikes_available": 4, "docks_available": 15, "ebikes_avaiable": 2}, {"station_id": "420", "bikes_available": 3, "docks_available": 15, "ebikes_avaiable": 0}, {"station_id": "423", "bikes_available": 0, "docks_available": 29, "ebikes_avaiable": 0}, {"station_id": "424", "bikes_available": 4, "docks_available": 21, "ebikes_avaiable": 0}, {"station_id": "425", "bikes_available": 10, "docks_available": 4, "ebikes_avaiable": 0}, {"station_id": "426", "bikes_available": 12, "docks_available": 7, "ebikes_avaiable": 2}]}, {"time": 1634960494.1151378, "data": [{"station_id": "328", "bikes_available": 0, "docks_available": 17, "ebikes_avaiable": 0}, {"station_id": "345", "bikes_available": 4, "docks_available": 15, "ebikes_avaiable": 2}, {"station_id": "420", "bikes_available": 3, "docks_available": 15, "ebikes_avaiable": 0}, {"station_id": "423", "bikes_available": 0, "docks_available": 29, "ebikes_avaiable": 0}, {"station_id": "424", "bikes_available": 4, "docks_available": 21, "ebikes_avaiable": 0}, {"station_id": "425", "bikes_available": 10, "docks_available": 4, "ebikes_avaiable": 0}, {"station_id": "426", "bikes_available": 12, "docks_available": 7, "ebikes_avaiable": 2}]}, {"time": 1634960554.845385, "data": [{"station_id": "328", "bikes_available": 0, "docks_available": 17, "ebikes_avaiable": 0}, {"station_id": "345", "bikes_available": 4, "docks_available": 15, "ebikes_avaiable": 2}, {"station_id": "420", "bikes_available": 3, "docks_available": 15, "ebikes_avaiable": 0}, {"station_id": "423", "bikes_available": 0, "docks_available": 29, "ebikes_avaiable": 0}, {"station_id": "424", "bikes_available": 4, "docks_available": 21, "ebikes_avaiable": 0}, {"station_id": "425", "bikes_available": 10, "docks_available": 4, "ebikes_avaiable": 0}, {"station_id": "426", "bikes_available": 12, "docks_available": 7, "ebikes_avaiable": 2}]}, {"time": 1634960615.4587057, "data": [{"station_id": "328", "bikes_available": 0, "docks_available": 17, "ebikes_avaiable": 0}, {"station_id": "345", "bikes_available": 4, "docks_available": 15, "ebikes_avaiable": 2}, {"station_id": "420", "bikes_available": 3, "docks_available": 15, "ebikes_avaiable": 0}, {"station_id": "423", "bikes_available": 0, "docks_available": 29, "ebikes_avaiable": 0}, {"station_id": "424", "bikes_available": 4, "docks_available": 21, "ebikes_avaiable": 0}, {"station_id": "425", "bikes_available": 10, "docks_available": 4, "ebikes_avaiable": 0}, {"station_id": "426", "bikes_available": 13, "docks_available": 6, "ebikes_avaiable": 3}]}, {"time": 1634960676.5809445, "data": [{"station_id": "328", "bikes_available": 0, "docks_available": 17, "ebikes_avaiable": 0}, {"station_id": "345", "bikes_available": 4, "docks_available": 15, "ebikes_avaiable": 2}, {"station_id": "420", "bikes_available": 3, "docks_available": 15, "ebikes_avaiable": 0}, {"station_id": "423", "bikes_available": 0, "docks_available": 29, "ebikes_avaiable": 0}, {"station_id": "424", "bikes_available": 4, "docks_available": 21, "ebikes_avaiable": 0}, {"station_id": "425", "bikes_available": 10, "docks_available": 4, "ebikes_avaiable": 0}, {"station_id": "426", "bikes_available": 13, "docks_available": 6, "ebikes_avaiable": 3}]}, {"time": 1634960737.24737, "data": [{"station_id": "328", "bikes_available": 0, "docks_available": 17, "ebikes_avaiable": 0}, {"station_id": "345", "bikes_available": 4, "docks_available": 15, "ebikes_avaiable": 2}, {"station_id": "420", "bikes_available": 3, "docks_available": 15, "ebikes_avaiable": 0}, {"station_id": "423", "bikes_available": 0, "docks_available": 29, "ebikes_avaiable": 0}, {"station_id": "424", "bikes_available": 4, "docks_available": 21, "ebikes_avaiable": 0}, {"station_id": "425", "bikes_available": 10, "docks_available": 4, "ebikes_avaiable": 0}, {"station_id": "426", "bikes_available": 13, "docks_available": 6, "ebikes_avaiable": 3}]}, {"time": 1634960797.9200573, "data": [{"station_id": "328", "bikes_available": 0, "docks_available": 17, "ebikes_avaiable": 0}, {"station_id": "345", "bikes_available": 4, "docks_available": 15, "ebikes_avaiable": 2}, {"station_id": "420", "bikes_available": 3, "docks_available": 15, "ebikes_avaiable": 0}, {"station_id": "423", "bikes_available": 0, "docks_available": 29, "ebikes_avaiable": 0}, {"station_id": "424", "bikes_available": 4, "docks_available": 21, "ebikes_avaiable": 0}, {"station_id": "425", "bikes_available": 10, "docks_available": 4, "ebikes_avaiable": 0}, {"station_id": "426", "bikes_available": 13, "docks_available": 6, "ebikes_avaiable": 3}]}, {"time": 1634960858.4565468, "data": [{"station_id": "328", "bikes_available": 0, "docks_available": 17, "ebikes_avaiable": 0}, {"station_id": "345", "bikes_available": 4, "docks_available": 15, "ebikes_avaiable": 2}, {"station_id": "420", "bikes_available": 3, "docks_available": 15, "ebikes_avaiable": 0}, {"station_id": "423", "bikes_available": 0, "docks_available": 29, "ebikes_avaiable": 0}, {"station_id": "424", "bikes_available": 4, "docks_available": 21, "ebikes_avaiable": 0}, {"station_id": "425", "bikes_available": 10, "docks_available": 4, "ebikes_avaiable": 0}, {"station_id": "426", "bikes_available": 10, "docks_available": 9, "ebikes_avaiable": 0}]}, {"time": 1634960919.1612825, "data": [{"station_id": "328", "bikes_available": 0, "docks_available": 17, "ebikes_avaiable": 0}, {"station_id": "345", "bikes_available": 4, "docks_available": 15, "ebikes_avaiable": 2}, {"station_id": "420", "bikes_available": 3, "docks_available": 15, "ebikes_avaiable": 0}, {"station_id": "423", "bikes_available": 0, "docks_available": 29, "ebikes_avaiable": 0}, {"station_id": "424", "bikes_available": 4, "docks_available": 21, "ebikes_avaiable": 0}, {"station_id": "425", "bikes_available": 10, "docks_available": 4, "ebikes_avaiable": 0}, {"station_id": "426", "bikes_available": 10, "docks_available": 9, "ebikes_avaiable": 0}]}, {"time": 1634960979.875183, "data": [{"station_id": "328", "bikes_available": 0, "docks_available": 17, "ebikes_avaiable": 0}, {"station_id": "345", "bikes_available": 4, "docks_available": 15, "ebikes_avaiable": 2}, {"station_id": "420", "bikes_available": 0, "docks_available": 18, "ebikes_avaiable": 0}, {"station_id": "423", "bikes_available": 0, "docks_available": 29, "ebikes_avaiable": 0}, {"station_id": "424", "bikes_available": 4, "docks_available": 21, "ebikes_avaiable": 0}, {"station_id": "425", "bikes_available": 10, "docks_available": 4, "ebikes_avaiable": 0}, {"station_id": "426", "bikes_available": 10, "docks_available": 9, "ebikes_avaiable": 0}]}, {"time": 1634961040.558479, "data": [{"station_id": "328", "bikes_available": 0, "docks_available": 17, "ebikes_avaiable": 0}, {"station_id": "345", "bikes_available": 4, "docks_available": 15, "ebikes_avaiable": 2}, {"station_id": "420", "bikes_available": 0, "docks_available": 18, "ebikes_avaiable": 0}, {"station_id": "423", "bikes_available": 0, "docks_available": 29, "ebikes_avaiable": 0}, {"station_id": "424", "bikes_available": 4, "docks_available": 21, "ebikes_avaiable": 0}, {"station_id": "425", "bikes_available": 10, "docks_available": 4, "ebikes_avaiable": 0}, {"station_id": "426", "bikes_available": 10, "docks_available": 9, "ebikes_avaiable": 0}]}, {"time": 1634961101.3052456, "data": [{"station_id": "328", "bikes_available": 0, "docks_available": 17, "ebikes_avaiable": 0}, {"station_id": "345", "bikes_available": 4, "docks_available": 15, "ebikes_avaiable": 2}, {"station_id": "420", "bikes_available": 0, "docks_available": 18, "ebikes_avaiable": 0}, {"station_id": "423", "bikes_available": 1, "docks_available": 28, "ebikes_avaiable": 0}, {"station_id": "424", "bikes_available": 4, "docks_available": 21, "ebikes_avaiable": 0}, {"station_id": "425", "bikes_available": 10, "docks_available": 4, "ebikes_avaiable": 0}, {"station_id": "426", "bikes_available": 10, "docks_available": 9, "ebikes_avaiable": 0}]}, {"time": 1634961161.9483109, "data": [{"station_id": "328", "bikes_available": 0, "docks_available": 17, "ebikes_avaiable": 0}, {"station_id": "345", "bikes_available": 4, "docks_available": 15, "ebikes_avaiable": 2}, {"station_id": "420", "bikes_available": 0, "docks_available": 18, "ebikes_avaiable": 0}, {"station_id": "423", "bikes_available": 1, "docks_available": 28, "ebikes_avaiable": 0}, {"station_id": "424", "bikes_available": 4, "docks_available": 21, "ebikes_avaiable": 0}, {"station_id": "425", "bikes_available": 10, "docks_available": 4, "ebikes_avaiable": 0}, {"station_id": "426", "bikes_available": 10, "docks_available": 9, "ebikes_avaiable": 0}]}, {"time": 1634961222.6724052, "data": [{"station_id": "328", "bikes_available": 0, "docks_available": 17, "ebikes_avaiable": 0}, {"station_id": "345", "bikes_available": 4, "docks_available": 15, "ebikes_avaiable": 2}, {"station_id": "420", "bikes_available": 0, "docks_available": 18, "ebikes_avaiable": 0}, {"station_id": "423", "bikes_available": 1, "docks_available": 28, "ebikes_avaiable": 0}, {"station_id": "424", "bikes_available": 4, "docks_available": 21, "ebikes_avaiable": 0}, {"station_id": "425", "bikes_available": 10, "docks_available": 4, "ebikes_avaiable": 0}, {"station_id": "426", "bikes_available": 10, "docks_available": 9, "ebikes_avaiable": 0}]}, {"time": 1634961283.34037, "data": [{"station_id": "328", "bikes_available": 0, "docks_available": 17, "ebikes_avaiable": 0}, {"station_id": "345", "bikes_available": 4, "docks_available": 15, "ebikes_avaiable": 2}, {"station_id": "420", "bikes_available": 0, "docks_available": 18, "ebikes_avaiable": 0}, {"station_id": "423", "bikes_available": 1, "docks_available": 28, "ebikes_avaiable": 0}, {"station_id": "424", "bikes_available": 4, "docks_available": 21, "ebikes_avaiable": 0}, {"station_id": "425", "bikes_available": 10, "docks_available": 4, "ebikes_avaiable": 0}, {"station_id": "426", "bikes_available": 11, "docks_available": 8, "ebikes_avaiable": 0}]}, {"time": 1634961344.0607343, "data": [{"station_id": "328", "bikes_available": 0, "docks_available": 17, "ebikes_avaiable": 0}, {"station_id": "345", "bikes_available": 4, "docks_available": 15, "ebikes_avaiable": 2}, {"station_id": "420", "bikes_available": 0, "docks_available": 18, "ebikes_avaiable": 0}, {"station_id": "423", "bikes_available": 1, "docks_available": 28, "ebikes_avaiable": 0}, {"station_id": "424", "bikes_available": 4, "docks_available": 21, "ebikes_avaiable": 0}, {"station_id": "425", "bikes_available": 10, "docks_available": 4, "ebikes_avaiable": 0}, {"station_id": "426", "bikes_available": 11, "docks_available": 8, "ebikes_avaiable": 0}]}, {"time": 1634961404.6844454, "data": [{"station_id": "328", "bikes_available": 0, "docks_available": 17, "ebikes_avaiable": 0}, {"station_id": "345", "bikes_available": 4, "docks_available": 15, "ebikes_avaiable": 2}, {"station_id": "420", "bikes_available": 0, "docks_available": 18, "ebikes_avaiable": 0}, {"station_id": "423", "bikes_available": 1, "docks_available": 28, "ebikes_avaiable": 0}, {"station_id": "424", "bikes_available": 4, "docks_available": 21, "ebikes_avaiable": 0}, {"station_id": "425", "bikes_available": 10, "docks_available": 4, "ebikes_avaiable": 0}, {"station_id": "426", "bikes_available": 11, "docks_available": 8, "ebikes_avaiable": 0}]}, {"time": 1634961465.3178847, "data": [{"station_id": "328", "bikes_available": 0, "docks_available": 17, "ebikes_avaiable": 0}, {"station_id": "345", "bikes_available": 4, "docks_available": 15, "ebikes_avaiable": 2}, {"station_id": "420", "bikes_available": 0, "docks_available": 18, "ebikes_avaiable": 0}, {"station_id": "423", "bikes_available": 1, "docks_available": 28, "ebikes_avaiable": 0}, {"station_id": "424", "bikes_available": 4, "docks_available": 21, "ebikes_avaiable": 0}, {"station_id": "425", "bikes_available": 10, "docks_available": 4, "ebikes_avaiable": 0}, {"station_id": "426", "bikes_available": 11, "docks_available": 8, "ebikes_avaiable": 0}]}, {"time": 1634961525.9099023, "data": [{"station_id": "328", "bikes_available": 0, "docks_available": 17, "ebikes_avaiable": 0}, {"station_id": "345", "bikes_available": 4, "docks_available": 15, "ebikes_avaiable": 2}, {"station_id": "420", "bikes_available": 0, "docks_available": 18, "ebikes_avaiable": 0}, {"station_id": "423", "bikes_available": 0, "docks_available": 29, "ebikes_avaiable": 0}, {"station_id": "424", "bikes_available": 4, "docks_available": 21, "ebikes_avaiable": 0}, {"station_id": "425", "bikes_available": 10, "docks_available": 4, "ebikes_avaiable": 0}, {"station_id": "426", "bikes_available": 11, "docks_available": 8, "ebikes_avaiable": 0}]}, {"time": 1634961586.5963619, "data": [{"station_id": "328", "bikes_available": 0, "docks_available": 17, "ebikes_avaiable": 0}, {"station_id": "345", "bikes_available": 4, "docks_available": 15, "ebikes_avaiable": 2}, {"station_id": "420", "bikes_available": 0, "docks_available": 18, "ebikes_avaiable": 0}, {"station_id": "423", "bikes_available": 0, "docks_available": 29, "ebikes_avaiable": 0}, {"station_id": "424", "bikes_available": 4, "docks_available": 21, "ebikes_avaiable": 0}, {"station_id": "425", "bikes_available": 10, "docks_available": 4, "ebikes_avaiable": 0}, {"station_id": "426", "bikes_available": 11, "docks_available": 8, "ebikes_avaiable": 0}]}]